README.md
setup.py
eidanagios/__init__.py
eidanagios/check_EIDA_alparray.py
eidanagios/check_EIDA_auth.py
eidanagios.egg-info/PKG-INFO
eidanagios.egg-info/SOURCES.txt
eidanagios.egg-info/dependency_links.txt
eidanagios.egg-info/entry_points.txt
eidanagios.egg-info/requires.txt
eidanagios.egg-info/top_level.txt