Metadata-Version: 2.1
Name: eidanagios
Version: 0.1a5
Summary: eidanagios: Nagios plugins and test code for EIDA services
Home-page: https://gitext.gfz-potsdam.de/javier/eidanagios
Author: Javier Quinteros
Author-email: javier@gfz-potsdam.de
License: GPLv3
Keywords: EIDA services Nagios
Platform: UNKNOWN
Classifier: Development Status :: 3 - Alpha
Classifier: Environment :: Console
Classifier: Intended Audience :: System Administrators
Classifier: License :: OSI Approved :: GNU General Public License v3 or later (GPLv3+)
Classifier: Natural Language :: English
Classifier: Operating System :: POSIX :: Linux
Classifier: Programming Language :: Python :: 3
Classifier: Programming Language :: Python :: 3.6
Classifier: Programming Language :: Python :: 3.7
Classifier: Topic :: System :: Monitoring
Provides: eidanagios
Requires-Python: >=3
